{
  "player": "Dani Masom",
  "slug": "dani-masom",
  "elo": 1487.25,
  "matches": [
    {
      "week": "25-12-6_brainstormin_charity_tournament",
      "round": 1,
      "opponent": "Graham Bateman",
      "result": "L",
      "score": 0.0,
      "elo_before": 1500.0,
      "elo_after": 1484.0,
      "opp_elo": 1500.0
    },
    {
      "week": "25-12-6_brainstormin_charity_tournament",
      "round": 2,
      "opponent": "Sean Marks",
      "result": "W",
      "score": 1.0,
      "elo_before": 1484.0,
      "elo_after": 1500.7363,
      "opp_elo": 1500.0
    },
    {
      "week": "25-12-6_brainstormin_charity_tournament",
      "round": 3,
      "opponent": "Austin Wolf",
      "result": "L",
      "score": 0.0,
      "elo_before": 1500.7363,
      "elo_after": 1484.7024,
      "opp_elo": 1500.0
    },
    {
      "week": "25-12-6_brainstormin_charity_tournament",
      "round": 4,
      "opponent": "Evan Johnstone",
      "result": "L",
      "score": 0.0,
      "elo_before": 1484.7024,
      "elo_after": 1468.7701,
      "opp_elo": 1486.1722
    },
    {
      "week": "25-12-6_brainstormin_charity_tournament",
      "round": 5,
      "opponent": "Phil Iwanow",
      "result": "W",
      "score": 1.0,
      "elo_before": 1468.7701,
      "elo_after": 1484.8331,
      "opp_elo": 1470.1383
    },
    {
      "week": "25-12-6_brainstormin_charity_tournament",
      "round": 6,
      "opponent": "Joseph Chung",
      "result": "W",
      "score": 1.0,
      "elo_before": 1484.8331,
      "elo_after": 1500.1613,
      "opp_elo": 1470.2364
    },
    {
      "week": "26-2-13",
      "round": 1,
      "opponent": "Stella Burfeind",
      "result": "L",
      "score": 0.0,
      "elo_before": 1500.1613,
      "elo_after": 1485.3758,
      "opp_elo": 1526.5846
    },
    {
      "week": "26-2-13",
      "round": 2,
      "opponent": "David Van Hise",
      "result": "L",
      "score": 0.0,
      "elo_before": 1485.3758,
      "elo_after": 1468.6484,
      "opp_elo": 1469.5703
    },
    {
      "week": "26-2-13",
      "round": 3,
      "opponent": "Willow Blackthorne",
      "result": "W",
      "score": 1.0,
      "elo_before": 1468.6484,
      "elo_after": 1486.0883,
      "opp_elo": 1500.0
    },
    {
      "week": "26-2-13",
      "round": 4,
      "opponent": "Hex Dowd",
      "result": "W",
      "score": 1.0,
      "elo_before": 1486.0883,
      "elo_after": 1502.1889,
      "opp_elo": 1488.2723
    },
    {
      "week": "26-2-13",
      "round": 5,
      "opponent": "Nathan Choi",
      "result": "L",
      "score": 0.0,
      "elo_before": 1502.1889,
      "elo_after": 1487.8169,
      "opp_elo": 1537.6632
    },
    {
      "week": "26-2-20",
      "round": 1,
      "opponent": "Ash DerManouelian",
      "result": "L",
      "score": 0.0,
      "elo_before": 1487.8169,
      "elo_after": 1472.3777,
      "opp_elo": 1500.0
    },
    {
      "week": "26-2-20",
      "round": 3,
      "opponent": "Jason Weiss",
      "result": "L",
      "score": 0.0,
      "elo_before": 1472.3777,
      "elo_after": 1457.6471,
      "opp_elo": 1500.0
    },
    {
      "week": "26-2-20",
      "round": 4,
      "opponent": "Stella Burfeind",
      "result": "W",
      "score": 1.0,
      "elo_before": 1457.6471,
      "elo_after": 1474.9279,
      "opp_elo": 1485.5197
    },
    {
      "week": "26-2-20",
      "round": 5,
      "opponent": "Mike Adams",
      "result": "W",
      "score": 1.0,
      "elo_before": 1474.9279,
      "elo_after": 1494.4077,
      "opp_elo": 1551.7158
    },
    {
      "week": "26-2-27",
      "round": 1,
      "opponent": "Nathan Choi",
      "result": "L",
      "score": 0.0,
      "elo_before": 1494.4077,
      "elo_after": 1481.0374,
      "opp_elo": 1552.0352
    },
    {
      "week": "26-2-27",
      "round": 2,
      "opponent": "Stan Kornacki",
      "result": "L",
      "score": 0.0,
      "elo_before": 1481.0374,
      "elo_after": 1469.1911,
      "opp_elo": 1573.3465
    },
    {
      "week": "26-2-27",
      "round": 3,
      "opponent": "Jarrod Haase",
      "result": "W",
      "score": 1.0,
      "elo_before": 1469.1911,
      "elo_after": 1481.8558,
      "opp_elo": 1395.687
    },
    {
      "week": "26-2-27",
      "round": 4,
      "opponent": "John Larochelle",
      "result": "L",
      "score": 0.0,
      "elo_before": 1481.8558,
      "elo_after": 1466.5586,
      "opp_elo": 1497.127
    },
    {
      "week": "26-3-07",
      "round": 1,
      "opponent": "Reya Truher",
      "result": "L",
      "score": 0.0,
      "elo_before": 1466.5586,
      "elo_after": 1452.3614,
      "opp_elo": 1505.8733
    },
    {
      "week": "26-3-07",
      "round": 2,
      "opponent": "Logan Hesch",
      "result": "L",
      "score": 0.0,
      "elo_before": 1452.3614,
      "elo_after": 1438.6434,
      "opp_elo": 1502.2539
    },
    {
      "week": "26-3-07",
      "round": 3,
      "opponent": "Daniel Hernandez",
      "result": "W",
      "score": 1.0,
      "elo_before": 1438.6434,
      "elo_after": 1455.2094,
      "opp_elo": 1450.9399
    },
    {
      "week": "26-3-07",
      "round": 4,
      "opponent": "Hex Dowd",
      "result": "L",
      "score": 0.0,
      "elo_before": 1455.2094,
      "elo_after": 1437.8151,
      "opp_elo": 1424.8554
    },
    {
      "week": "26-3-07",
      "round": 5,
      "opponent": "Sean Thornton",
      "result": "W",
      "score": 1.0,
      "elo_before": 1437.8151,
      "elo_after": 1456.6486,
      "opp_elo": 1500.0
    },
    {
      "week": "26-3-13",
      "round": 1,
      "opponent": "Jarrod Haase",
      "result": "W",
      "score": 1.0,
      "elo_before": 1456.6486,
      "elo_after": 1470.5698,
      "opp_elo": 1411.2502
    },
    {
      "week": "26-3-13",
      "round": 2,
      "opponent": "Sam Feeley",
      "result": "W",
      "score": 1.0,
      "elo_before": 1470.5698,
      "elo_after": 1488.6501,
      "opp_elo": 1516.0
    },
    {
      "week": "26-3-13",
      "round": 3,
      "opponent": "Bradley Skubic",
      "result": "L",
      "score": 0.0,
      "elo_before": 1488.6501,
      "elo_after": 1477.9498,
      "opp_elo": 1608.2411
    },
    {
      "week": "26-3-13",
      "round": 4,
      "opponent": "James Farley",
      "result": "W",
      "score": 1.0,
      "elo_before": 1477.9498,
      "elo_after": 1494.9639,
      "opp_elo": 1500.0
    },
    {
      "week": "26-3-13",
      "round": 5,
      "opponent": "Anthony Wilkinson",
      "result": "L",
      "score": 0.0,
      "elo_before": 1494.9639,
      "elo_after": 1487.2454,
      "opp_elo": 1694.0625
    }
  ],
  "wins": 13,
  "losses": 16,
  "draws": 0
}