{
  "player": "Daniel Hernandez",
  "slug": "daniel-hernandez",
  "elo": 1434.72,
  "matches": [
    {
      "week": "25-12-6_brainstormin_charity_tournament",
      "round": 1,
      "opponent": "Jack Henry",
      "result": "L",
      "score": 0.0,
      "elo_before": 1500.0,
      "elo_after": 1484.0,
      "opp_elo": 1500.0
    },
    {
      "week": "25-12-6_brainstormin_charity_tournament",
      "round": 2,
      "opponent": "Danielle Lucibello",
      "result": "W",
      "score": 1.0,
      "elo_before": 1484.0,
      "elo_after": 1500.7363,
      "opp_elo": 1500.0
    },
    {
      "week": "25-12-6_brainstormin_charity_tournament",
      "round": 3,
      "opponent": "Philip Petronis",
      "result": "W",
      "score": 1.0,
      "elo_before": 1500.7363,
      "elo_after": 1516.7024,
      "opp_elo": 1500.0
    },
    {
      "week": "25-12-6_brainstormin_charity_tournament",
      "round": 4,
      "opponent": "Ryan MacDonald",
      "result": "L",
      "score": 0.0,
      "elo_before": 1516.7024,
      "elo_after": 1500.7024,
      "opp_elo": 1516.7024
    },
    {
      "week": "25-12-6_brainstormin_charity_tournament",
      "round": 5,
      "opponent": "Isharah Considine",
      "result": "L",
      "score": 0.0,
      "elo_before": 1500.7024,
      "elo_after": 1484.6701,
      "opp_elo": 1500.0016
    },
    {
      "week": "25-12-6_brainstormin_charity_tournament",
      "round": 6,
      "opponent": "Jarrod Haase",
      "result": "W",
      "score": 1.0,
      "elo_before": 1484.6701,
      "elo_after": 1500.6084,
      "opp_elo": 1483.3299
    },
    {
      "week": "26-2-13",
      "round": 1,
      "opponent": "Autumn Garofalo",
      "result": "L",
      "score": 0.0,
      "elo_before": 1500.6084,
      "elo_after": 1484.5804,
      "opp_elo": 1500.0
    },
    {
      "week": "26-2-13",
      "round": 2,
      "opponent": "Jack Henry",
      "result": "L",
      "score": 0.0,
      "elo_before": 1484.5804,
      "elo_after": 1468.5467,
      "opp_elo": 1483.8486
    },
    {
      "week": "26-2-13",
      "round": 3,
      "opponent": "Milo Brown",
      "result": "L",
      "score": 0.0,
      "elo_before": 1468.5467,
      "elo_after": 1455.865,
      "opp_elo": 1541.6626
    },
    {
      "week": "26-2-27",
      "round": 1,
      "opponent": "Jack Henry",
      "result": "L",
      "score": 0.0,
      "elo_before": 1455.865,
      "elo_after": 1439.7823,
      "opp_elo": 1454.0699
    },
    {
      "week": "26-2-27",
      "round": 2,
      "opponent": "Joseph Chung",
      "result": "W",
      "score": 1.0,
      "elo_before": 1439.7823,
      "elo_after": 1455.6814,
      "opp_elo": 1437.5924
    },
    {
      "week": "26-2-27",
      "round": 3,
      "opponent": "Sean Thornton",
      "result": "W",
      "score": 1.0,
      "elo_before": 1455.6814,
      "elo_after": 1473.7114,
      "opp_elo": 1500.0
    },
    {
      "week": "26-2-27",
      "round": 4,
      "opponent": "Stan Kornacki",
      "result": "L",
      "score": 0.0,
      "elo_before": 1473.7114,
      "elo_after": 1463.2102,
      "opp_elo": 1598.1819
    },
    {
      "week": "26-2-27",
      "round": 5,
      "opponent": "Nathan Cormier",
      "result": "W",
      "score": 1.0,
      "elo_before": 1463.2102,
      "elo_after": 1481.85,
      "opp_elo": 1521.0605
    },
    {
      "week": "26-3-07",
      "round": 1,
      "opponent": "Stan Kornacki",
      "result": "L",
      "score": 0.0,
      "elo_before": 1481.85,
      "elo_after": 1471.8901,
      "opp_elo": 1619.8352
    },
    {
      "week": "26-3-07",
      "round": 2,
      "opponent": "Jarrod Haase",
      "result": "L",
      "score": 0.0,
      "elo_before": 1471.8901,
      "elo_after": 1450.942,
      "opp_elo": 1360.8059
    },
    {
      "week": "26-3-07",
      "round": 3,
      "opponent": "Dani Masom",
      "result": "L",
      "score": 0.0,
      "elo_before": 1450.942,
      "elo_after": 1434.3759,
      "opp_elo": 1438.6452
    },
    {
      "week": "26-3-07",
      "round": 4,
      "opponent": "Evan Johnstone",
      "result": "W",
      "score": 1.0,
      "elo_before": 1434.3759,
      "elo_after": 1448.36,
      "opp_elo": 1390.3671
    },
    {
      "week": "26-3-07",
      "round": 5,
      "opponent": "Philip Watson",
      "result": "L",
      "score": 0.0,
      "elo_before": 1448.36,
      "elo_after": 1434.7208,
      "opp_elo": 1500.0
    }
  ],
  "wins": 7,
  "losses": 12,
  "draws": 0
}