{
  "player": "Evan Johnstone",
  "slug": "evan-johnstone",
  "elo": 1458.55,
  "matches": [
    {
      "week": "25-12-6_brainstormin_charity_tournament",
      "round": 1,
      "opponent": "Avi Lessure",
      "result": "L",
      "score": 0.0,
      "elo_before": 1500.0,
      "elo_after": 1481.0,
      "opp_elo": 1500.0,
      "is_bye": false
    },
    {
      "week": "25-12-6_brainstormin_charity_tournament",
      "round": 2,
      "opponent": "Jonathon Streker",
      "result": "L",
      "score": 0.0,
      "elo_before": 1481.0,
      "elo_after": 1463.038,
      "opp_elo": 1500.0,
      "is_bye": false
    },
    {
      "week": "25-12-6_brainstormin_charity_tournament",
      "round": 3,
      "opponent": "Timothy Haase",
      "result": "W",
      "score": 1.0,
      "elo_before": 1463.038,
      "elo_after": 1484.0517,
      "opp_elo": 1500.0,
      "is_bye": false
    },
    {
      "week": "25-12-6_brainstormin_charity_tournament",
      "round": 4,
      "opponent": "Dani Masom",
      "result": "W",
      "score": 1.0,
      "elo_before": 1484.0517,
      "elo_after": 1502.9354,
      "opp_elo": 1481.9245,
      "is_bye": false
    },
    {
      "week": "25-12-6_brainstormin_charity_tournament",
      "round": 5,
      "opponent": "David Van Hise",
      "result": "W",
      "score": 1.0,
      "elo_before": 1502.9354,
      "elo_after": 1521.8316,
      "opp_elo": 1501.038,
      "is_bye": false
    },
    {
      "week": "25-12-6_brainstormin_charity_tournament",
      "round": 6,
      "opponent": "Ran Guo",
      "result": "L",
      "score": 0.0,
      "elo_before": 1521.8316,
      "elo_after": 1502.826,
      "opp_elo": 1521.7282,
      "is_bye": false
    },
    {
      "week": "26-2-13",
      "round": 1,
      "opponent": "Devon O'Donnell",
      "result": "L",
      "score": 0.0,
      "elo_before": 1502.826,
      "elo_after": 1483.6714,
      "opp_elo": 1500.0,
      "is_bye": false
    },
    {
      "week": "26-2-13",
      "round": 2,
      "opponent": "Sean Marks",
      "result": "W",
      "score": 1.0,
      "elo_before": 1483.6714,
      "elo_after": 1503.5637,
      "opp_elo": 1500.0,
      "is_bye": false
    },
    {
      "week": "26-2-13",
      "round": 3,
      "opponent": "Jarrod Haase",
      "result": "L",
      "score": 0.0,
      "elo_before": 1503.5637,
      "elo_after": 1481.5525,
      "opp_elo": 1448.0309,
      "is_bye": false
    },
    {
      "week": "26-2-13",
      "round": 4,
      "opponent": "Amber Cronin",
      "result": "L",
      "score": 0.0,
      "elo_before": 1481.5525,
      "elo_after": 1459.4671,
      "opp_elo": 1424.6298,
      "is_bye": false
    },
    {
      "week": "26-2-13",
      "round": 5,
      "opponent": "Hex Dowd",
      "result": "W",
      "score": 1.0,
      "elo_before": 1459.4671,
      "elo_after": 1478.9192,
      "opp_elo": 1467.7354,
      "is_bye": false
    },
    {
      "week": "26-2-20",
      "round": 1,
      "opponent": "Jonathon Streker",
      "result": "W",
      "score": 1.0,
      "elo_before": 1478.9192,
      "elo_after": 1499.0706,
      "opp_elo": 1500.0,
      "is_bye": false
    },
    {
      "week": "26-2-20",
      "round": 2,
      "opponent": "Nathan Cormier",
      "result": "L",
      "score": 0.0,
      "elo_before": 1499.0706,
      "elo_after": 1479.1235,
      "opp_elo": 1481.7367,
      "is_bye": false
    },
    {
      "week": "26-2-20",
      "round": 3,
      "opponent": "Mike Adams",
      "result": "L",
      "score": 0.0,
      "elo_before": 1479.1235,
      "elo_after": 1464.8306,
      "opp_elo": 1567.0281,
      "is_bye": false
    },
    {
      "week": "26-2-20",
      "round": 4,
      "opponent": "Sean Marks",
      "result": "L",
      "score": 0.0,
      "elo_before": 1464.8306,
      "elo_after": 1447.7474,
      "opp_elo": 1500.0,
      "is_bye": false
    },
    {
      "week": "26-2-20",
      "round": 5,
      "opponent": "Hex Dowd",
      "result": "L",
      "score": 0.0,
      "elo_before": 1447.7474,
      "elo_after": 1426.5865,
      "opp_elo": 1408.062,
      "is_bye": false
    },
    {
      "week": "26-2-27",
      "round": 1,
      "opponent": "Isharah Considine",
      "result": "L",
      "score": 0.0,
      "elo_before": 1426.5865,
      "elo_after": 1412.7258,
      "opp_elo": 1522.9618,
      "is_bye": false
    },
    {
      "week": "26-2-27",
      "round": 2,
      "opponent": "Nathan Cormier",
      "result": "L",
      "score": 0.0,
      "elo_before": 1412.7258,
      "elo_after": 1398.833,
      "opp_elo": 1508.4683,
      "is_bye": false
    },
    {
      "week": "26-2-27",
      "round": 3,
      "opponent": "Pan Rasking",
      "result": "W",
      "score": 1.0,
      "elo_before": 1398.833,
      "elo_after": 1422.7618,
      "opp_elo": 1491.0689,
      "is_bye": false
    },
    {
      "week": "26-2-27",
      "round": 4,
      "opponent": "Hex Dowd",
      "result": "L",
      "score": 0.0,
      "elo_before": 1422.7618,
      "elo_after": 1403.7124,
      "opp_elo": 1421.8594,
      "is_bye": false
    },
    {
      "week": "26-2-27",
      "round": 5,
      "opponent": "Phil Iwanow",
      "result": "W",
      "score": 1.0,
      "elo_before": 1403.7124,
      "elo_after": 1422.191,
      "opp_elo": 1394.1743,
      "is_bye": false
    },
    {
      "week": "26-3-07",
      "round": 1,
      "opponent": "Chris Daniel",
      "result": "L",
      "score": 0.0,
      "elo_before": 1422.191,
      "elo_after": 1407.3763,
      "opp_elo": 1500.0,
      "is_bye": false
    },
    {
      "week": "26-3-07",
      "round": 2,
      "opponent": "Patrick Brooks",
      "result": "L",
      "score": 0.0,
      "elo_before": 1407.3763,
      "elo_after": 1392.3433,
      "opp_elo": 1481.0,
      "is_bye": false
    },
    {
      "week": "26-3-07",
      "round": 3,
      "opponent": "Hex Dowd",
      "result": "L",
      "score": 0.0,
      "elo_before": 1392.3433,
      "elo_after": 1373.6583,
      "opp_elo": 1398.1028,
      "is_bye": false
    },
    {
      "week": "26-3-07",
      "round": 4,
      "opponent": "Daniel Hernandez",
      "result": "L",
      "score": 0.0,
      "elo_before": 1373.6583,
      "elo_after": 1357.3998,
      "opp_elo": 1424.1422,
      "is_bye": false
    },
    {
      "week": "26-3-07",
      "round": 5,
      "opponent": "Pan Rasking",
      "result": "D",
      "score": 0.5,
      "elo_before": 1357.3998,
      "elo_after": 1360.2194,
      "opp_elo": 1409.344,
      "is_bye": false
    },
    {
      "week": "26-3-20",
      "round": 1,
      "opponent": "Milo Brown",
      "result": "W",
      "score": 1.0,
      "elo_before": 1360.2194,
      "elo_after": 1392.2367,
      "opp_elo": 1651.6135,
      "is_bye": false
    },
    {
      "week": "26-3-20",
      "round": 2,
      "opponent": "Amy Altman",
      "result": "W",
      "score": 1.0,
      "elo_before": 1392.2367,
      "elo_after": 1422.27,
      "opp_elo": 1622.765,
      "is_bye": false
    },
    {
      "week": "26-3-20",
      "round": 3,
      "opponent": "Anthony Wilkinson",
      "result": "L",
      "score": 0.0,
      "elo_before": 1422.27,
      "elo_after": 1417.0102,
      "opp_elo": 1739.9151,
      "is_bye": false
    },
    {
      "week": "26-3-20",
      "round": 4,
      "opponent": "Patrick Brooks",
      "result": "W",
      "score": 1.0,
      "elo_before": 1417.0102,
      "elo_after": 1440.0033,
      "opp_elo": 1491.1335,
      "is_bye": false
    },
    {
      "week": "26-3-20",
      "round": 5,
      "opponent": "Will Bellows",
      "result": "L",
      "score": 0.0,
      "elo_before": 1440.0033,
      "elo_after": 1424.2521,
      "opp_elo": 1500.0,
      "is_bye": false
    },
    {
      "week": "26-4-10",
      "round": 1,
      "opponent": "Jonathon Torchia",
      "result": "W",
      "score": 1.0,
      "elo_before": 1424.2521,
      "elo_after": 1447.3301,
      "opp_elo": 1500.0,
      "is_bye": false
    },
    {
      "week": "26-4-10",
      "round": 2,
      "opponent": "[REDACTED] [REDACTED]",
      "result": "W",
      "score": 1.0,
      "elo_before": 1447.3301,
      "elo_after": 1469.1885,
      "opp_elo": 1500.0,
      "is_bye": false
    },
    {
      "week": "26-4-10",
      "round": 3,
      "opponent": "Dylan Shanes",
      "result": "L",
      "score": 0.0,
      "elo_before": 1469.1885,
      "elo_after": 1451.8691,
      "opp_elo": 1500.0,
      "is_bye": false
    },
    {
      "week": "26-4-10",
      "round": 4,
      "opponent": "Autumn Rossa",
      "result": "L",
      "score": 0.0,
      "elo_before": 1451.8691,
      "elo_after": 1438.1144,
      "opp_elo": 1550.3409,
      "is_bye": false
    },
    {
      "week": "26-4-10",
      "round": 5,
      "opponent": "Gina Millott",
      "result": "W",
      "score": 1.0,
      "elo_before": 1438.1144,
      "elo_after": 1458.5543,
      "opp_elo": 1464.4936,
      "is_bye": false
    }
  ],
  "wins": 14,
  "losses": 21,
  "draws": 1
}