{
  "player": "Ryan MacDonald",
  "slug": "ryan-macdonald",
  "elo": 1507.18,
  "games": 9,
  "wins": 5,
  "losses": 4,
  "ties": 0,
  "matches": [
    {
      "week": "25-12-6_brainstormin_charity_tournament",
      "round": 1,
      "opponent": "Amy Altman",
      "result": "L",
      "score": 0.0,
      "elo_before": 1500.0,
      "elo_after": 1484.0
    },
    {
      "week": "25-12-6_brainstormin_charity_tournament",
      "round": 2,
      "opponent": "John Petrella",
      "result": "W",
      "score": 1.0,
      "elo_before": 1484.0,
      "elo_after": 1500.7363
    },
    {
      "week": "25-12-6_brainstormin_charity_tournament",
      "round": 3,
      "opponent": "Michael Stopa",
      "result": "W",
      "score": 1.0,
      "elo_before": 1500.7363,
      "elo_after": 1516.7024
    },
    {
      "week": "25-12-6_brainstormin_charity_tournament",
      "round": 4,
      "opponent": "Daniel Hernandez",
      "result": "W",
      "score": 1.0,
      "elo_before": 1516.7024,
      "elo_after": 1531.9338
    },
    {
      "week": "25-12-6_brainstormin_charity_tournament",
      "round": 5,
      "opponent": "Jack Henry",
      "result": "W",
      "score": 1.0,
      "elo_before": 1531.9338,
      "elo_after": 1547.9354
    },
    {
      "week": "25-12-6_brainstormin_charity_tournament",
      "round": 6,
      "opponent": "Brian Kennes",
      "result": "W",
      "score": 1.0,
      "elo_before": 1547.9354,
      "elo_after": 1561.7418
    },
    {
      "week": "26-2-13",
      "round": 1,
      "opponent": "Thomas Kotcher",
      "result": "L",
      "score": 0.0,
      "elo_before": 1561.7418,
      "elo_after": 1542.928
    },
    {
      "week": "26-2-13",
      "round": 2,
      "opponent": "Isharah Considine",
      "result": "L",
      "score": 0.0,
      "elo_before": 1542.928,
      "elo_after": 1524.2985
    },
    {
      "week": "26-2-13",
      "round": 3,
      "opponent": "Sean Thornton",
      "result": "L",
      "score": 0.0,
      "elo_before": 1524.2985,
      "elo_after": 1507.1813
    }
  ]
}