[
  {
    "player": "Bradley Skubic",
    "elo": 1650.17,
    "matches": 31,
    "wins": 20,
    "losses": 5,
    "draws": 6
  },
  {
    "player": "Ran Guo",
    "elo": 1645.71,
    "matches": 16,
    "wins": 12,
    "losses": 3,
    "draws": 1
  },
  {
    "player": "David Van Hise",
    "elo": 1645.0,
    "matches": 39,
    "wins": 27,
    "losses": 12,
    "draws": 0
  },
  {
    "player": "Kenton Najdzien",
    "elo": 1639.6,
    "matches": 30,
    "wins": 20,
    "losses": 9,
    "draws": 1
  },
  {
    "player": "Amy Altman",
    "elo": 1630.96,
    "matches": 51,
    "wins": 30,
    "losses": 15,
    "draws": 6
  },
  {
    "player": "Kevin Thanakit",
    "elo": 1621.51,
    "matches": 10,
    "wins": 8,
    "losses": 2,
    "draws": 0
  },
  {
    "player": "Milo Brown",
    "elo": 1601.52,
    "matches": 36,
    "wins": 22,
    "losses": 10,
    "draws": 4
  },
  {
    "player": "Anthony Wilkinson",
    "elo": 1600.05,
    "matches": 61,
    "wins": 40,
    "losses": 18,
    "draws": 3
  },
  {
    "player": "Stan Kornacki",
    "elo": 1589.6,
    "matches": 46,
    "wins": 28,
    "losses": 15,
    "draws": 3
  },
  {
    "player": "Autumn Rossa",
    "elo": 1572.23,
    "matches": 15,
    "wins": 9,
    "losses": 4,
    "draws": 2
  },
  {
    "player": "Nathan Choi",
    "elo": 1570.46,
    "matches": 55,
    "wins": 35,
    "losses": 17,
    "draws": 3
  },
  {
    "player": "Taylor Pratt",
    "elo": 1568.08,
    "matches": 10,
    "wins": 7,
    "losses": 2,
    "draws": 1
  },
  {
    "player": "Logan Hesch",
    "elo": 1563.95,
    "matches": 39,
    "wins": 23,
    "losses": 16,
    "draws": 0
  },
  {
    "player": "Ethan Ford",
    "elo": 1555.37,
    "matches": 5,
    "wins": 4,
    "losses": 1,
    "draws": 0
  },
  {
    "player": "Becca Blackwood",
    "elo": 1545.26,
    "matches": 48,
    "wins": 26,
    "losses": 18,
    "draws": 4
  },
  {
    "player": "Mike Adams",
    "elo": 1545.18,
    "matches": 54,
    "wins": 25,
    "losses": 22,
    "draws": 7
  },
  {
    "player": "Jeffrey Silver",
    "elo": 1539.74,
    "matches": 10,
    "wins": 6,
    "losses": 4,
    "draws": 0
  },
  {
    "player": "Isharah Considine",
    "elo": 1539.26,
    "matches": 25,
    "wins": 13,
    "losses": 11,
    "draws": 1
  },
  {
    "player": "Hex Dowd",
    "elo": 1527.07,
    "matches": 59,
    "wins": 26,
    "losses": 32,
    "draws": 1
  },
  {
    "player": "Bailey Sarkis",
    "elo": 1519.71,
    "matches": 7,
    "wins": 4,
    "losses": 3,
    "draws": 0
  },
  {
    "player": "Graham Bateman",
    "elo": 1516.21,
    "matches": 6,
    "wins": 3,
    "losses": 2,
    "draws": 1
  },
  {
    "player": "Nathan Cormier",
    "elo": 1513.35,
    "matches": 42,
    "wins": 20,
    "losses": 20,
    "draws": 2
  },
  {
    "player": "Timofey Tylik",
    "elo": 1510.5,
    "matches": 9,
    "wins": 4,
    "losses": 4,
    "draws": 1
  },
  {
    "player": "Mike Laing",
    "elo": 1508.63,
    "matches": 47,
    "wins": 23,
    "losses": 23,
    "draws": 1
  },
  {
    "player": "Ryan MacDonald",
    "elo": 1507.6,
    "matches": 9,
    "wins": 5,
    "losses": 4,
    "draws": 0
  },
  {
    "player": "Sam Feeley",
    "elo": 1506.33,
    "matches": 8,
    "wins": 4,
    "losses": 4,
    "draws": 0
  },
  {
    "player": "Stella Burfeind",
    "elo": 1502.4,
    "matches": 49,
    "wins": 22,
    "losses": 23,
    "draws": 4
  },
  {
    "player": "James Blanchfield",
    "elo": 1500.0,
    "matches": 0,
    "wins": 0,
    "losses": 0,
    "draws": 0
  },
  {
    "player": "Jonathan Ma",
    "elo": 1500.0,
    "matches": 0,
    "wins": 0,
    "losses": 0,
    "draws": 0
  },
  {
    "player": "Lucas Yang",
    "elo": 1500.0,
    "matches": 0,
    "wins": 0,
    "losses": 0,
    "draws": 0
  },
  {
    "player": "Austin Wolf",
    "elo": 1498.8,
    "matches": 6,
    "wins": 3,
    "losses": 3,
    "draws": 0
  },
  {
    "player": "Winston Wong",
    "elo": 1498.0,
    "matches": 21,
    "wins": 9,
    "losses": 10,
    "draws": 2
  },
  {
    "player": "Veronica Kirtley",
    "elo": 1494.74,
    "matches": 11,
    "wins": 5,
    "losses": 5,
    "draws": 1
  },
  {
    "player": "Joel Brook",
    "elo": 1491.58,
    "matches": 8,
    "wins": 4,
    "losses": 4,
    "draws": 0
  },
  {
    "player": "Raul Bottrell-Rogers",
    "elo": 1472.7,
    "matches": 26,
    "wins": 12,
    "losses": 14,
    "draws": 0
  },
  {
    "player": "Pan Rasking",
    "elo": 1472.2,
    "matches": 28,
    "wins": 11,
    "losses": 14,
    "draws": 3
  },
  {
    "player": "Dani Masom",
    "elo": 1471.94,
    "matches": 53,
    "wins": 24,
    "losses": 28,
    "draws": 1
  },
  {
    "player": "John Larochelle",
    "elo": 1470.02,
    "matches": 19,
    "wins": 8,
    "losses": 9,
    "draws": 2
  },
  {
    "player": "Elias Medrano",
    "elo": 1464.8,
    "matches": 6,
    "wins": 2,
    "losses": 4,
    "draws": 0
  },
  {
    "player": "Amber Cronin",
    "elo": 1459.51,
    "matches": 15,
    "wins": 5,
    "losses": 9,
    "draws": 1
  },
  {
    "player": "Andy Perez",
    "elo": 1459.26,
    "matches": 15,
    "wins": 5,
    "losses": 8,
    "draws": 2
  },
  {
    "player": "Evan Johnstone",
    "elo": 1458.56,
    "matches": 36,
    "wins": 14,
    "losses": 21,
    "draws": 1
  },
  {
    "player": "Gina Millott",
    "elo": 1444.04,
    "matches": 26,
    "wins": 11,
    "losses": 15,
    "draws": 0
  },
  {
    "player": "Terry Eleftherakis",
    "elo": 1440.94,
    "matches": 24,
    "wins": 9,
    "losses": 15,
    "draws": 0
  },
  {
    "player": "Reya Truher",
    "elo": 1440.87,
    "matches": 40,
    "wins": 17,
    "losses": 22,
    "draws": 1
  },
  {
    "player": "Patrick Brooks",
    "elo": 1436.39,
    "matches": 14,
    "wins": 5,
    "losses": 9,
    "draws": 0
  },
  {
    "player": "Phil Iwanow",
    "elo": 1435.63,
    "matches": 43,
    "wins": 13,
    "losses": 26,
    "draws": 4
  },
  {
    "player": "Jack Henry",
    "elo": 1396.46,
    "matches": 36,
    "wins": 13,
    "losses": 22,
    "draws": 1
  },
  {
    "player": "Jarrod Haase",
    "elo": 1392.91,
    "matches": 46,
    "wins": 14,
    "losses": 29,
    "draws": 3
  },
  {
    "player": "Joseph Chung",
    "elo": 1392.53,
    "matches": 18,
    "wins": 5,
    "losses": 13,
    "draws": 0
  },
  {
    "player": "Daniel Hernandez",
    "elo": 1302.05,
    "matches": 50,
    "wins": 13,
    "losses": 36,
    "draws": 1
  }
]